pyecho/__init__.py
pyecho_cli-0.1.1.dist-info/METADATA
pyecho_cli-0.1.1.dist-info/WHEEL
pyecho_cli-0.1.1.dist-info/entry_points.txt
pyecho_cli-0.1.1.dist-info/RECORD
