Metadata-Version: 2.3
Name: pyecho-cli
Version: 0.1.1
Summary: A simple echo script mainly exist for test.
Project-URL: Repository, https://github.com/j178/pyecho.git
Author-email: j178 <10510431+j178@users.noreply.github.com>
License-Expression: MIT
Requires-Python: >=3.8
